[{"domain":null,"method":"GET|HEAD","uri":"\/","name":null,"action":"Closure","middleware":["web"]},{"domain":null,"method":"GET|HEAD","uri":"api\/admin\/books","name":null,"action":"App\\Http\\Controllers\\Admin\\BookController@index","middleware":["api","Illuminate\\Auth\\Middleware\\Authenticate:sanctum","App\\Http\\Middleware\\AdminMiddleware"]},{"domain":null,"method":"GET|HEAD","uri":"api\/admin\/books\/{book}","name":null,"action":"App\\Http\\Controllers\\Admin\\BookController@show","middleware":["api","Illuminate\\Auth\\Middleware\\Authenticate:sanctum","App\\Http\\Middleware\\AdminMiddleware"]},{"domain":null,"method":"PUT","uri":"api\/admin\/books\/{book}","name":null,"action":"App\\Http\\Controllers\\Admin\\BookController@update","middleware":["api","Illuminate\\Auth\\Middleware\\Authenticate:sanctum","App\\Http\\Middleware\\AdminMiddleware"]},{"domain":null,"method":"DELETE","uri":"api\/admin\/books\/{book}","name":null,"action":"App\\Http\\Controllers\\Admin\\BookController@destroy","middleware":["api","Illuminate\\Auth\\Middleware\\Authenticate:sanctum","App\\Http\\Middleware\\AdminMiddleware"]},{"domain":null,"method":"PUT","uri":"api\/admin\/books\/{book}\/approve","name":null,"action":"App\\Http\\Controllers\\Admin\\BookController@approve","middleware":["api","Illuminate\\Auth\\Middleware\\Authenticate:sanctum","App\\Http\\Middleware\\AdminMiddleware"]},{"domain":null,"method":"PUT","uri":"api\/admin\/books\/{book}\/reject","name":null,"action":"App\\Http\\Controllers\\Admin\\BookController@reject","middleware":["api","Illuminate\\Auth\\Middleware\\Authenticate:sanctum","App\\Http\\Middleware\\AdminMiddleware"]},{"domain":null,"method":"GET|HEAD","uri":"api\/admin\/categories","name":"categories.index","action":"App\\Http\\Controllers\\Admin\\CategoryController@index","middleware":["api","Illuminate\\Auth\\Middleware\\Authenticate:sanctum","App\\Http\\Middleware\\AdminMiddleware"]},{"domain":null,"method":"POST","uri":"api\/admin\/categories","name":"categories.store","action":"App\\Http\\Controllers\\Admin\\CategoryController@store","middleware":["api","Illuminate\\Auth\\Middleware\\Authenticate:sanctum","App\\Http\\Middleware\\AdminMiddleware"]},{"domain":null,"method":"GET|HEAD","uri":"api\/admin\/categories\/{category}","name":"categories.show","action":"App\\Http\\Controllers\\Admin\\CategoryController@show","middleware":["api","Illuminate\\Auth\\Middleware\\Authenticate:sanctum","App\\Http\\Middleware\\AdminMiddleware"]},{"domain":null,"method":"PUT|PATCH","uri":"api\/admin\/categories\/{category}","name":"categories.update","action":"App\\Http\\Controllers\\Admin\\CategoryController@update","middleware":["api","Illuminate\\Auth\\Middleware\\Authenticate:sanctum","App\\Http\\Middleware\\AdminMiddleware"]},{"domain":null,"method":"DELETE","uri":"api\/admin\/categories\/{category}","name":"categories.destroy","action":"App\\Http\\Controllers\\Admin\\CategoryController@destroy","middleware":["api","Illuminate\\Auth\\Middleware\\Authenticate:sanctum","App\\Http\\Middleware\\AdminMiddleware"]},{"domain":null,"method":"GET|HEAD","uri":"api\/admin\/stats","name":null,"action":"App\\Http\\Controllers\\Admin\\DashboardController@stats","middleware":["api","Illuminate\\Auth\\Middleware\\Authenticate:sanctum","App\\Http\\Middleware\\AdminMiddleware"]},{"domain":null,"method":"GET|HEAD","uri":"api\/admin\/users","name":null,"action":"App\\Http\\Controllers\\Admin\\UserController@index","middleware":["api","Illuminate\\Auth\\Middleware\\Authenticate:sanctum","App\\Http\\Middleware\\AdminMiddleware"]},{"domain":null,"method":"GET|HEAD","uri":"api\/admin\/users\/{user}","name":null,"action":"App\\Http\\Controllers\\Admin\\UserController@show","middleware":["api","Illuminate\\Auth\\Middleware\\Authenticate:sanctum","App\\Http\\Middleware\\AdminMiddleware"]},{"domain":null,"method":"GET|HEAD","uri":"api\/books","name":null,"action":"App\\Http\\Controllers\\BookController@index","middleware":["api"]},{"domain":null,"method":"POST","uri":"api\/books","name":null,"action":"App\\Http\\Controllers\\User\\BookController@store","middleware":["api","Illuminate\\Auth\\Middleware\\Authenticate:sanctum"]},{"domain":null,"method":"GET|HEAD","uri":"api\/books\/{book}","name":null,"action":"App\\Http\\Controllers\\BookController@show","middleware":["api"]},{"domain":null,"method":"GET|HEAD","uri":"api\/books\/{book}\/reviews","name":null,"action":"App\\Http\\Controllers\\User\\ReviewController@index","middleware":["api"]},{"domain":null,"method":"POST","uri":"api\/books\/{book}\/reviews","name":null,"action":"App\\Http\\Controllers\\User\\ReviewController@store","middleware":["api","Illuminate\\Auth\\Middleware\\Authenticate:sanctum"]},{"domain":null,"method":"GET|HEAD","uri":"api\/cart","name":null,"action":"App\\Http\\Controllers\\User\\CartController@index","middleware":["api","Illuminate\\Auth\\Middleware\\Authenticate:sanctum"]},{"domain":null,"method":"POST","uri":"api\/cart\/books\/{book}","name":null,"action":"App\\Http\\Controllers\\User\\CartController@add","middleware":["api","Illuminate\\Auth\\Middleware\\Authenticate:sanctum"]},{"domain":null,"method":"DELETE","uri":"api\/cart\/books\/{book}","name":null,"action":"App\\Http\\Controllers\\User\\CartController@remove","middleware":["api","Illuminate\\Auth\\Middleware\\Authenticate:sanctum"]},{"domain":null,"method":"POST","uri":"api\/cart\/checkout","name":null,"action":"App\\Http\\Controllers\\User\\CartController@checkout","middleware":["api","Illuminate\\Auth\\Middleware\\Authenticate:sanctum"]},{"domain":null,"method":"GET|HEAD","uri":"api\/categories","name":null,"action":"App\\Http\\Controllers\\CategoryController@index","middleware":["api"]},{"domain":null,"method":"GET|HEAD","uri":"api\/collections","name":null,"action":"App\\Http\\Controllers\\User\\CollectionController@index","middleware":["api","Illuminate\\Auth\\Middleware\\Authenticate:sanctum"]},{"domain":null,"method":"GET|HEAD","uri":"api\/collections\/{collection}\/books","name":null,"action":"App\\Http\\Controllers\\User\\CollectionController@books","middleware":["api","Illuminate\\Auth\\Middleware\\Authenticate:sanctum"]},{"domain":null,"method":"POST","uri":"api\/collections\/{collection}\/books","name":null,"action":"App\\Http\\Controllers\\User\\CollectionController@addBook","middleware":["api","Illuminate\\Auth\\Middleware\\Authenticate:sanctum"]},{"domain":null,"method":"DELETE","uri":"api\/collections\/{collection}\/books\/{book}","name":null,"action":"App\\Http\\Controllers\\User\\CollectionController@removeBook","middleware":["api","Illuminate\\Auth\\Middleware\\Authenticate:sanctum"]},{"domain":null,"method":"GET|HEAD","uri":"api\/library","name":null,"action":"App\\Http\\Controllers\\User\\LibraryController@index","middleware":["api","Illuminate\\Auth\\Middleware\\Authenticate:sanctum"]},{"domain":null,"method":"GET|HEAD","uri":"api\/library\/{book}\/download","name":null,"action":"App\\Http\\Controllers\\User\\LibraryController@download","middleware":["api","Illuminate\\Auth\\Middleware\\Authenticate:sanctum"]},{"domain":null,"method":"POST","uri":"api\/login","name":null,"action":"App\\Http\\Controllers\\AuthController@login","middleware":["api"]},{"domain":null,"method":"POST","uri":"api\/logout","name":null,"action":"App\\Http\\Controllers\\AuthController@logout","middleware":["api","Illuminate\\Auth\\Middleware\\Authenticate:sanctum"]},{"domain":null,"method":"GET|HEAD","uri":"api\/my-books","name":null,"action":"App\\Http\\Controllers\\User\\MyBookController@index","middleware":["api","Illuminate\\Auth\\Middleware\\Authenticate:sanctum"]},{"domain":null,"method":"DELETE","uri":"api\/my-books\/{book}","name":null,"action":"App\\Http\\Controllers\\User\\MyBookController@destroy","middleware":["api","Illuminate\\Auth\\Middleware\\Authenticate:sanctum"]},{"domain":null,"method":"GET|HEAD","uri":"api\/orders","name":null,"action":"App\\Http\\Controllers\\User\\OrderController@index","middleware":["api","Illuminate\\Auth\\Middleware\\Authenticate:sanctum"]},{"domain":null,"method":"GET|HEAD","uri":"api\/orders\/{order}","name":null,"action":"App\\Http\\Controllers\\User\\OrderController@show","middleware":["api","Illuminate\\Auth\\Middleware\\Authenticate:sanctum"]},{"domain":null,"method":"GET|HEAD","uri":"api\/preferences","name":null,"action":"App\\Http\\Controllers\\User\\PreferenceController@show","middleware":["api","Illuminate\\Auth\\Middleware\\Authenticate:sanctum"]},{"domain":null,"method":"PUT","uri":"api\/preferences","name":null,"action":"App\\Http\\Controllers\\User\\PreferenceController@update","middleware":["api","Illuminate\\Auth\\Middleware\\Authenticate:sanctum"]},{"domain":null,"method":"GET|HEAD","uri":"api\/profile","name":null,"action":"App\\Http\\Controllers\\User\\ProfileController@show","middleware":["api","Illuminate\\Auth\\Middleware\\Authenticate:sanctum"]},{"domain":null,"method":"PUT","uri":"api\/profile","name":null,"action":"App\\Http\\Controllers\\User\\ProfileController@update","middleware":["api","Illuminate\\Auth\\Middleware\\Authenticate:sanctum"]},{"domain":null,"method":"POST","uri":"api\/profile\/avatar","name":null,"action":"App\\Http\\Controllers\\User\\ProfileController@uploadAvatar","middleware":["api","Illuminate\\Auth\\Middleware\\Authenticate:sanctum"]},{"domain":null,"method":"DELETE","uri":"api\/profile\/avatar","name":null,"action":"App\\Http\\Controllers\\User\\ProfileController@deleteAvatar","middleware":["api","Illuminate\\Auth\\Middleware\\Authenticate:sanctum"]},{"domain":null,"method":"GET|HEAD","uri":"api\/progress","name":null,"action":"App\\Http\\Controllers\\User\\ProgressController@index","middleware":["api","Illuminate\\Auth\\Middleware\\Authenticate:sanctum"]},{"domain":null,"method":"GET|HEAD","uri":"api\/progress\/{book}","name":null,"action":"App\\Http\\Controllers\\User\\ProgressController@show","middleware":["api","Illuminate\\Auth\\Middleware\\Authenticate:sanctum"]},{"domain":null,"method":"PUT","uri":"api\/progress\/{book}","name":null,"action":"App\\Http\\Controllers\\User\\ProgressController@update","middleware":["api","Illuminate\\Auth\\Middleware\\Authenticate:sanctum"]},{"domain":null,"method":"POST","uri":"api\/register","name":null,"action":"App\\Http\\Controllers\\AuthController@register","middleware":["api"]},{"domain":null,"method":"PUT","uri":"api\/reviews\/{review}","name":null,"action":"App\\Http\\Controllers\\User\\ReviewController@update","middleware":["api","Illuminate\\Auth\\Middleware\\Authenticate:sanctum"]},{"domain":null,"method":"DELETE","uri":"api\/reviews\/{review}","name":null,"action":"App\\Http\\Controllers\\User\\ReviewController@destroy","middleware":["api","Illuminate\\Auth\\Middleware\\Authenticate:sanctum"]},{"domain":null,"method":"GET|HEAD","uri":"api\/user","name":null,"action":"App\\Http\\Controllers\\AuthController@user","middleware":["api","Illuminate\\Auth\\Middleware\\Authenticate:sanctum"]},{"domain":null,"method":"GET|HEAD","uri":"sanctum\/csrf-cookie","name":"sanctum.csrf-cookie","action":"Laravel\\Sanctum\\Http\\Controllers\\CsrfCookieController@show","middleware":["web"]},{"domain":null,"method":"GET|HEAD","uri":"storage\/{path}","name":"storage.local","action":"Closure","middleware":[]},{"domain":null,"method":"GET|HEAD","uri":"up","name":null,"action":"Closure","middleware":[]}]
